{"version":1,"keyboard":{"keys":[{"id":0,"legend":"Q","state":{"x":0,"y":0,"r":0,"rx":0,"ry":0,"w":1,"h":1,"x2":0,"y2":0,"w2":0,"h2":0,"a":7},"row":0,"col":0,"keycodes":[{"id":"KC_Q","fields":[]},{"id":"KC_1","fields":[]},{"id":"KC_EXLM","fields":[]},{"id":"KC_TRNS","fields":[]},{"id":"KC_TRNS","fields":[]},{"id":"KC_TRNS","fields":[]},{"id":"KC_TRNS","fields":[]},{"id":"KC_TRNS","fields":[]},{"id":"KC_TRNS","fields":[]},{"id":"KC_TRNS","fields":[]},{"id":"KC_TRNS","fields":[]},{"id":"KC_TRNS","fields":[]},{"id":"KC_TRNS","fields":[]},{"id":"KC_TRNS","fields":[]},{"id":"KC_TRNS","fields":[]},{"id":"KC_TRNS","fields":[]}]},{"id":1,"legend":"W","state":{"x":1,"y":0,"r":0,"rx":0,"ry":0,"w":1,"h":1,"x2":0,"y2":0,"w2":0,"h2":0,"a":7},"row":0,"col":1,"keycodes":[{"id":"KC_W","fields":[]},{"id":"KC_2","fields":[]},{"id":"KC_AT","fields":[]},{"id":"KC_TRNS","fields":[]},{"id":"KC_TRNS","fields":[]},{"id":"KC_TRNS","fields":[]},{"id":"KC_TRNS","fields":[]},{"id":"KC_TRNS","fields":[]},{"id":"KC_TRNS","fields":[]},{"id":"KC_TRNS","fields":[]},{"id":"KC_TRNS","fields":[]},{"id":"KC_TRNS","fields":[]},{"id":"KC_TRNS","fields":[]},{"id":"KC_TRNS","fields":[]},{"id":"KC_TRNS","fields":[]},{"id":"KC_TRNS","fields":[]}]},{"id":2,"legend":"E","state":{"x":2,"y":0,"r":0,"rx":0,"ry":0,"w":1,"h":1,"x2":0,"y2":0,"w2":0,"h2":0,"a":7},"row":0,"col":2,"keycodes":[{"id":"KC_E","fields":[]},{"id":"KC_3","fields":[]},{"id":"KC_HASH","fields":[]},{"id":"KC_TRNS","fields":[]},{"id":"KC_TRNS","fields":[]},{"id":"KC_TRNS","fields":[]},{"id":"KC_TRNS","fields":[]},{"id":"KC_TRNS","fields":[]},{"id":"KC_TRNS","fields":[]},{"id":"KC_TRNS","fields":[]},{"id":"KC_TRNS","fields":[]},{"id":"KC_TRNS","fields":[]},{"id":"KC_TRNS","fields":[]},{"id":"KC_TRNS","fields":[]},{"id":"KC_TRNS","fields":[]},{"id":"KC_TRNS","fields":[]}]},{"id":3,"legend":"R","state":{"x":3,"y":0,"r":0,"rx":0,"ry":0,"w":1,"h":1,"x2":0,"y2":0,"w2":0,"h2":0,"a":7},"row":0,"col":3,"keycodes":[{"id":"KC_R","fields":[]},{"id":"KC_4","fields":[]},{"id":"KC_DLR","fields":[]},{"id":"KC_TRNS","fields":[]},{"id":"KC_TRNS","fields":[]},{"id":"KC_TRNS","fields":[]},{"id":"KC_TRNS","fields":[]},{"id":"KC_TRNS","fields":[]},{"id":"KC_TRNS","fields":[]},{"id":"KC_TRNS","fields":[]},{"id":"KC_TRNS","fields":[]},{"id":"KC_TRNS","fields":[]},{"id":"KC_TRNS","fields":[]},{"id":"KC_TRNS","fields":[]},{"id":"KC_TRNS","fields":[]},{"id":"KC_TRNS","fields":[]}]},{"id":4,"legend":"T","state":{"x":4,"y":0,"r":0,"rx":0,"ry":0,"w":1,"h":1,"x2":0,"y2":0,"w2":0,"h2":0,"a":7},"row":0,"col":4,"keycodes":[{"id":"KC_T","fields":[]},{"id":"KC_5","fields":[]},{"id":"KC_PERC","fields":[]},{"id":"KC_TRNS","fields":[]},{"id":"KC_TRNS","fields":[]},{"id":"KC_TRNS","fields":[]},{"id":"KC_TRNS","fields":[]},{"id":"KC_TRNS","fields":[]},{"id":"KC_TRNS","fields":[]},{"id":"KC_TRNS","fields":[]},{"id":"KC_TRNS","fields":[]},{"id":"KC_TRNS","fields":[]},{"id":"KC_TRNS","fields":[]},{"id":"KC_TRNS","fields":[]},{"id":"KC_TRNS","fields":[]},{"id":"KC_TRNS","fields":[]}]},{"id":5,"legend":"Y","state":{"x":5,"y":0,"r":0,"rx":0,"ry":0,"w":1,"h":1,"x2":0,"y2":0,"w2":0,"h2":0,"a":7},"row":0,"col":5,"keycodes":[{"id":"KC_Y","fields":[]},{"id":"KC_6","fields":[]},{"id":"KC_CIRC","fields":[]},{"id":"KC_TRNS","fields":[]},{"id":"KC_TRNS","fields":[]},{"id":"KC_TRNS","fields":[]},{"id":"KC_TRNS","fields":[]},{"id":"KC_TRNS","fields":[]},{"id":"KC_TRNS","fields":[]},{"id":"KC_TRNS","fields":[]},{"id":"KC_TRNS","fields":[]},{"id":"KC_TRNS","fields":[]},{"id":"KC_TRNS","fields":[]},{"id":"KC_TRNS","fields":[]},{"id":"KC_TRNS","fields":[]},{"id":"KC_TRNS","fields":[]}]},{"id":6,"legend":"U","state":{"x":6,"y":0,"r":0,"rx":0,"ry":0,"w":1,"h":1,"x2":0,"y2":0,"w2":0,"h2":0,"a":7},"row":0,"col":6,"keycodes":[{"id":"KC_U","fields":[]},{"id":"KC_7","fields":[]},{"id":"KC_AMPR","fields":[]},{"id":"KC_TRNS","fields":[]},{"id":"KC_TRNS","fields":[]},{"id":"KC_TRNS","fields":[]},{"id":"KC_TRNS","fields":[]},{"id":"KC_TRNS","fields":[]},{"id":"KC_TRNS","fields":[]},{"id":"KC_TRNS","fields":[]},{"id":"KC_TRNS","fields":[]},{"id":"KC_TRNS","fields":[]},{"id":"KC_TRNS","fields":[]},{"id":"KC_TRNS","fields":[]},{"id":"KC_TRNS","fields":[]},{"id":"KC_TRNS","fields":[]}]},{"id":7,"legend":"I","state":{"x":7,"y":0,"r":0,"rx":0,"ry":0,"w":1,"h":1,"x2":0,"y2":0,"w2":0,"h2":0,"a":7},"row":0,"col":7,"keycodes":[{"id":"KC_I","fields":[]},{"id":"KC_8","fields":[]},{"id":"KC_ASTR","fields":[]},{"id":"KC_TRNS","fields":[]},{"id":"KC_TRNS","fields":[]},{"id":"KC_TRNS","fields":[]},{"id":"KC_TRNS","fields":[]},{"id":"KC_TRNS","fields":[]},{"id":"KC_TRNS","fields":[]},{"id":"KC_TRNS","fields":[]},{"id":"KC_TRNS","fields":[]},{"id":"KC_TRNS","fields":[]},{"id":"KC_TRNS","fields":[]},{"id":"KC_TRNS","fields":[]},{"id":"KC_TRNS","fields":[]},{"id":"KC_TRNS","fields":[]}]},{"id":8,"legend":"O","state":{"x":8,"y":0,"r":0,"rx":0,"ry":0,"w":1,"h":1,"x2":0,"y2":0,"w2":0,"h2":0,"a":7},"row":0,"col":8,"keycodes":[{"id":"KC_O","fields":[]},{"id":"KC_9","fields":[]},{"id":"KC_LPRN","fields":[]},{"id":"KC_TRNS","fields":[]},{"id":"KC_TRNS","fields":[]},{"id":"KC_TRNS","fields":[]},{"id":"KC_TRNS","fields":[]},{"id":"KC_TRNS","fields":[]},{"id":"KC_TRNS","fields":[]},{"id":"KC_TRNS","fields":[]},{"id":"KC_TRNS","fields":[]},{"id":"KC_TRNS","fields":[]},{"id":"KC_TRNS","fields":[]},{"id":"KC_TRNS","fields":[]},{"id":"KC_TRNS","fields":[]},{"id":"KC_TRNS","fields":[]}]},{"id":9,"legend":"P","state":{"x":9,"y":0,"r":0,"rx":0,"ry":0,"w":1,"h":1,"x2":0,"y2":0,"w2":0,"h2":0,"a":7},"row":0,"col":9,"keycodes":[{"id":"KC_P","fields":[]},{"id":"KC_0","fields":[]},{"id":"KC_RPRN","fields":[]},{"id":"KC_TRNS","fields":[]},{"id":"KC_TRNS","fields":[]},{"id":"KC_TRNS","fields":[]},{"id":"KC_TRNS","fields":[]},{"id":"KC_TRNS","fields":[]},{"id":"KC_TRNS","fields":[]},{"id":"KC_TRNS","fields":[]},{"id":"KC_TRNS","fields":[]},{"id":"KC_TRNS","fields":[]},{"id":"KC_TRNS","fields":[]},{"id":"KC_TRNS","fields":[]},{"id":"KC_TRNS","fields":[]},{"id":"KC_TRNS","fields":[]}]},{"id":10,"legend":"Back Space","state":{"x":10,"y":0,"r":0,"rx":0,"ry":0,"w":1,"h":1,"x2":0,"y2":0,"w2":0,"h2":0,"a":7},"row":0,"col":10,"keycodes":[{"id":"KC_BSPC","fields":[]},{"id":"KC_DEL","fields":[]},{"id":"KC_ESC","fields":[]},{"id":"KC_TRNS","fields":[]},{"id":"KC_TRNS","fields":[]},{"id":"KC_TRNS","fields":[]},{"id":"KC_TRNS","fields":[]},{"id":"KC_TRNS","fields":[]},{"id":"KC_TRNS","fields":[]},{"id":"KC_TRNS","fields":[]},{"id":"KC_TRNS","fields":[]},{"id":"KC_TRNS","fields":[]},{"id":"KC_TRNS","fields":[]},{"id":"KC_TRNS","fields":[]},{"id":"KC_TRNS","fields":[]},{"id":"KC_TRNS","fields":[]}]},{"id":11,"legend":"A","state":{"x":0,"y":1,"r":0,"rx":0,"ry":0,"w":1,"h":1,"x2":0,"y2":0,"w2":0,"h2":0,"a":7},"row":1,"col":0,"keycodes":[{"id":"KC_A","fields":[]},{"id":"KC_VOLU","fields":[]},{"id":"KC_GRV","fields":[]},{"id":"KC_TRNS","fields":[]},{"id":"KC_TRNS","fields":[]},{"id":"KC_TRNS","fields":[]},{"id":"KC_TRNS","fields":[]},{"id":"KC_TRNS","fields":[]},{"id":"KC_TRNS","fields":[]},{"id":"KC_TRNS","fields":[]},{"id":"KC_TRNS","fields":[]},{"id":"KC_TRNS","fields":[]},{"id":"KC_TRNS","fields":[]},{"id":"KC_TRNS","fields":[]},{"id":"KC_TRNS","fields":[]},{"id":"KC_TRNS","fields":[]}]},{"id":12,"legend":"S","state":{"x":1,"y":1,"r":0,"rx":0,"ry":0,"w":1,"h":1,"x2":0,"y2":0,"w2":0,"h2":0,"a":7},"row":1,"col":1,"keycodes":[{"id":"KC_S","fields":[]},{"id":"KC_LBRC","fields":[]},{"id":"KC_LCBR","fields":[]},{"id":"KC_TRNS","fields":[]},{"id":"KC_TRNS","fields":[]},{"id":"KC_TRNS","fields":[]},{"id":"KC_TRNS","fields":[]},{"id":"KC_TRNS","fields":[]},{"id":"KC_TRNS","fields":[]},{"id":"KC_TRNS","fields":[]},{"id":"KC_TRNS","fields":[]},{"id":"KC_TRNS","fields":[]},{"id":"KC_TRNS","fields":[]},{"id":"KC_TRNS","fields":[]},{"id":"KC_TRNS","fields":[]},{"id":"KC_TRNS","fields":[]}]},{"id":13,"legend":"D","state":{"x":2,"y":1,"r":0,"rx":0,"ry":0,"w":1,"h":1,"x2":0,"y2":0,"w2":0,"h2":0,"a":7},"row":1,"col":2,"keycodes":[{"id":"KC_D","fields":[]},{"id":"KC_RBRC","fields":[]},{"id":"KC_RCBR","fields":[]},{"id":"KC_TRNS","fields":[]},{"id":"KC_TRNS","fields":[]},{"id":"KC_TRNS","fields":[]},{"id":"KC_TRNS","fields":[]},{"id":"KC_TRNS","fields":[]},{"id":"KC_TRNS","fields":[]},{"id":"KC_TRNS","fields":[]},{"id":"KC_TRNS","fields":[]},{"id":"KC_TRNS","fields":[]},{"id":"KC_TRNS","fields":[]},{"id":"KC_TRNS","fields":[]},{"id":"KC_TRNS","fields":[]},{"id":"KC_TRNS","fields":[]}]},{"id":14,"legend":"F","state":{"x":3,"y":1,"r":0,"rx":0,"ry":0,"w":1,"h":1,"x2":0,"y2":0,"w2":0,"h2":0,"a":7},"row":1,"col":3,"keycodes":[{"id":"KC_F","fields":[]},{"id":"KC_EQL","fields":[]},{"id":"KC_PLUS","fields":[]},{"id":"KC_TRNS","fields":[]},{"id":"KC_TRNS","fields":[]},{"id":"KC_TRNS","fields":[]},{"id":"KC_TRNS","fields":[]},{"id":"KC_TRNS","fields":[]},{"id":"KC_TRNS","fields":[]},{"id":"KC_TRNS","fields":[]},{"id":"KC_TRNS","fields":[]},{"id":"KC_TRNS","fields":[]},{"id":"KC_TRNS","fields":[]},{"id":"KC_TRNS","fields":[]},{"id":"KC_TRNS","fields":[]},{"id":"KC_TRNS","fields":[]}]},{"id":15,"legend":"G","state":{"x":4,"y":1,"r":0,"rx":0,"ry":0,"w":1,"h":1,"x2":0,"y2":0,"w2":0,"h2":0,"a":7},"row":1,"col":4,"keycodes":[{"id":"KC_G","fields":[]},{"id":"KC_MINS","fields":[]},{"id":"KC_UNDS","fields":[]},{"id":"KC_TRNS","fields":[]},{"id":"KC_TRNS","fields":[]},{"id":"KC_TRNS","fields":[]},{"id":"KC_TRNS","fields":[]},{"id":"KC_TRNS","fields":[]},{"id":"KC_TRNS","fields":[]},{"id":"KC_TRNS","fields":[]},{"id":"KC_TRNS","fields":[]},{"id":"KC_TRNS","fields":[]},{"id":"KC_TRNS","fields":[]},{"id":"KC_TRNS","fields":[]},{"id":"KC_TRNS","fields":[]},{"id":"KC_TRNS","fields":[]}]},{"id":16,"legend":"H","state":{"x":5,"y":1,"r":0,"rx":0,"ry":0,"w":1,"h":1,"x2":0,"y2":0,"w2":0,"h2":0,"a":7},"row":1,"col":5,"keycodes":[{"id":"KC_H","fields":[]},{"id":"KC_BSLS","fields":[]},{"id":"KC_PIPE","fields":[]},{"id":"KC_TRNS","fields":[]},{"id":"KC_TRNS","fields":[]},{"id":"KC_TRNS","fields":[]},{"id":"KC_TRNS","fields":[]},{"id":"KC_TRNS","fields":[]},{"id":"KC_TRNS","fields":[]},{"id":"KC_TRNS","fields":[]},{"id":"KC_TRNS","fields":[]},{"id":"KC_TRNS","fields":[]},{"id":"KC_TRNS","fields":[]},{"id":"KC_TRNS","fields":[]},{"id":"KC_TRNS","fields":[]},{"id":"KC_TRNS","fields":[]}]},{"id":17,"legend":"J","state":{"x":6,"y":1,"r":0,"rx":0,"ry":0,"w":1,"h":1,"x2":0,"y2":0,"w2":0,"h2":0,"a":7},"row":1,"col":6,"keycodes":[{"id":"KC_J","fields":[]},{"id":"KC_LEFT","fields":[]},{"id":"RGB_HUI","fields":[]},{"id":"KC_TRNS","fields":[]},{"id":"KC_TRNS","fields":[]},{"id":"KC_TRNS","fields":[]},{"id":"KC_TRNS","fields":[]},{"id":"KC_TRNS","fields":[]},{"id":"KC_TRNS","fields":[]},{"id":"KC_TRNS","fields":[]},{"id":"KC_TRNS","fields":[]},{"id":"KC_TRNS","fields":[]},{"id":"KC_TRNS","fields":[]},{"id":"KC_TRNS","fields":[]},{"id":"KC_TRNS","fields":[]},{"id":"KC_TRNS","fields":[]}]},{"id":18,"legend":"K","state":{"x":7,"y":1,"r":0,"rx":0,"ry":0,"w":1,"h":1,"x2":0,"y2":0,"w2":0,"h2":0,"a":7},"row":1,"col":7,"keycodes":[{"id":"KC_K","fields":[]},{"id":"KC_UP","fields":[]},{"id":"RGB_HUD","fields":[]},{"id":"KC_TRNS","fields":[]},{"id":"KC_TRNS","fields":[]},{"id":"KC_TRNS","fields":[]},{"id":"KC_TRNS","fields":[]},{"id":"KC_TRNS","fields":[]},{"id":"KC_TRNS","fields":[]},{"id":"KC_TRNS","fields":[]},{"id":"KC_TRNS","fields":[]},{"id":"KC_TRNS","fields":[]},{"id":"KC_TRNS","fields":[]},{"id":"KC_TRNS","fields":[]},{"id":"KC_TRNS","fields":[]},{"id":"KC_TRNS","fields":[]}]},{"id":19,"legend":"L","state":{"x":8,"y":1,"r":0,"rx":0,"ry":0,"w":1,"h":1,"x2":0,"y2":0,"w2":0,"h2":0,"a":7},"row":1,"col":8,"keycodes":[{"id":"KC_L","fields":[]},{"id":"KC_RGHT","fields":[]},{"id":"RGB_SAI","fields":[]},{"id":"KC_TRNS","fields":[]},{"id":"KC_TRNS","fields":[]},{"id":"KC_TRNS","fields":[]},{"id":"KC_TRNS","fields":[]},{"id":"KC_TRNS","fields":[]},{"id":"KC_TRNS","fields":[]},{"id":"KC_TRNS","fields":[]},{"id":"KC_TRNS","fields":[]},{"id":"KC_TRNS","fields":[]},{"id":"KC_TRNS","fields":[]},{"id":"KC_TRNS","fields":[]},{"id":"KC_TRNS","fields":[]},{"id":"KC_TRNS","fields":[]}]},{"id":20,"legend":";","state":{"x":9,"y":1,"r":0,"rx":0,"ry":0,"w":1,"h":1,"x2":0,"y2":0,"w2":0,"h2":0,"a":7},"row":1,"col":9,"keycodes":[{"id":"KC_ENT","fields":[]},{"id":"KC_TRNS","fields":[]},{"id":"RGB_SAD","fields":[]},{"id":"KC_TRNS","fields":[]},{"id":"KC_TRNS","fields":[]},{"id":"KC_TRNS","fields":[]},{"id":"KC_TRNS","fields":[]},{"id":"KC_TRNS","fields":[]},{"id":"KC_TRNS","fields":[]},{"id":"KC_TRNS","fields":[]},{"id":"KC_TRNS","fields":[]},{"id":"KC_TRNS","fields":[]},{"id":"KC_TRNS","fields":[]},{"id":"KC_TRNS","fields":[]},{"id":"KC_TRNS","fields":[]},{"id":"KC_TRNS","fields":[]}]},{"id":21,"legend":"'","state":{"x":10,"y":1,"r":0,"rx":0,"ry":0,"w":1,"h":1,"x2":0,"y2":0,"w2":0,"h2":0,"a":7},"row":1,"col":10,"keycodes":[{"id":"KC_RCTL","fields":[]},{"id":"KC_NUHS","fields":[]},{"id":"KC_NUBS","fields":[]},{"id":"KC_TRNS","fields":[]},{"id":"KC_TRNS","fields":[]},{"id":"KC_TRNS","fields":[]},{"id":"KC_TRNS","fields":[]},{"id":"KC_TRNS","fields":[]},{"id":"KC_TRNS","fields":[]},{"id":"KC_TRNS","fields":[]},{"id":"KC_TRNS","fields":[]},{"id":"KC_TRNS","fields":[]},{"id":"KC_TRNS","fields":[]},{"id":"KC_TRNS","fields":[]},{"id":"KC_TRNS","fields":[]},{"id":"KC_TRNS","fields":[]}]},{"id":22,"legend":"Z","state":{"x":0,"y":2,"r":0,"rx":0,"ry":0,"w":1,"h":1,"x2":0,"y2":0,"w2":0,"h2":0,"a":7},"row":2,"col":0,"keycodes":[{"id":"MT()","fields":[2,{"id":"KC_Z","fields":[]}]},{"id":"KC_VOLD","fields":[]},{"id":"KC_TILD","fields":[]},{"id":"KC_TRNS","fields":[]},{"id":"KC_TRNS","fields":[]},{"id":"KC_TRNS","fields":[]},{"id":"KC_TRNS","fields":[]},{"id":"KC_TRNS","fields":[]},{"id":"KC_TRNS","fields":[]},{"id":"KC_TRNS","fields":[]},{"id":"KC_TRNS","fields":[]},{"id":"KC_TRNS","fields":[]},{"id":"KC_TRNS","fields":[]},{"id":"KC_TRNS","fields":[]},{"id":"KC_TRNS","fields":[]},{"id":"KC_TRNS","fields":[]}]},{"id":23,"legend":"X","state":{"x":1,"y":2,"r":0,"rx":0,"ry":0,"w":1,"h":1,"x2":0,"y2":0,"w2":0,"h2":0,"a":7},"row":2,"col":1,"keycodes":[{"id":"KC_X","fields":[]},{"id":"KC_SLSH","fields":[]},{"id":"KC_QUES","fields":[]},{"id":"KC_TRNS","fields":[]},{"id":"KC_TRNS","fields":[]},{"id":"KC_TRNS","fields":[]},{"id":"KC_TRNS","fields":[]},{"id":"KC_TRNS","fields":[]},{"id":"KC_TRNS","fields":[]},{"id":"KC_TRNS","fields":[]},{"id":"KC_TRNS","fields":[]},{"id":"KC_TRNS","fields":[]},{"id":"KC_TRNS","fields":[]},{"id":"KC_TRNS","fields":[]},{"id":"KC_TRNS","fields":[]},{"id":"KC_TRNS","fields":[]}]},{"id":24,"legend":"C","state":{"x":2,"y":2,"r":0,"rx":0,"ry":0,"w":1,"h":1,"x2":0,"y2":0,"w2":0,"h2":0,"a":7},"row":2,"col":2,"keycodes":[{"id":"KC_C","fields":[]},{"id":"KC_SCLN","fields":[]},{"id":"KC_COLN","fields":[]},{"id":"KC_TRNS","fields":[]},{"id":"KC_TRNS","fields":[]},{"id":"KC_TRNS","fields":[]},{"id":"KC_TRNS","fields":[]},{"id":"KC_TRNS","fields":[]},{"id":"KC_TRNS","fields":[]},{"id":"KC_TRNS","fields":[]},{"id":"KC_TRNS","fields":[]},{"id":"KC_TRNS","fields":[]},{"id":"KC_TRNS","fields":[]},{"id":"KC_TRNS","fields":[]},{"id":"KC_TRNS","fields":[]},{"id":"KC_TRNS","fields":[]}]},{"id":25,"legend":"V","state":{"x":3,"y":2,"r":0,"rx":0,"ry":0,"w":1,"h":1,"x2":0,"y2":0,"w2":0,"h2":0,"a":7},"row":2,"col":3,"keycodes":[{"id":"KC_V","fields":[]},{"id":"KC_QUOT","fields":[]},{"id":"KC_DQUO","fields":[]},{"id":"KC_TRNS","fields":[]},{"id":"KC_TRNS","fields":[]},{"id":"KC_TRNS","fields":[]},{"id":"KC_TRNS","fields":[]},{"id":"KC_TRNS","fields":[]},{"id":"KC_TRNS","fields":[]},{"id":"KC_TRNS","fields":[]},{"id":"KC_TRNS","fields":[]},{"id":"KC_TRNS","fields":[]},{"id":"KC_TRNS","fields":[]},{"id":"KC_TRNS","fields":[]},{"id":"KC_TRNS","fields":[]},{"id":"KC_TRNS","fields":[]}]},{"id":26,"legend":"B","state":{"x":4,"y":2,"r":0,"rx":0,"ry":0,"w":1,"h":1,"x2":0,"y2":0,"w2":0,"h2":0,"a":7},"row":2,"col":4,"keycodes":[{"id":"KC_B","fields":[]},{"id":"KC_LABK","fields":[]},{"id":"LGUI()","fields":[{"id":"KC_TAB","fields":[]}]},{"id":"KC_TRNS","fields":[]},{"id":"KC_TRNS","fields":[]},{"id":"KC_TRNS","fields":[]},{"id":"KC_TRNS","fields":[]},{"id":"KC_TRNS","fields":[]},{"id":"KC_TRNS","fields":[]},{"id":"KC_TRNS","fields":[]},{"id":"KC_TRNS","fields":[]},{"id":"KC_TRNS","fields":[]},{"id":"KC_TRNS","fields":[]},{"id":"KC_TRNS","fields":[]},{"id":"KC_TRNS","fields":[]},{"id":"KC_TRNS","fields":[]}]},{"id":27,"legend":"N","state":{"x":5,"y":2,"r":0,"rx":0,"ry":0,"w":1,"h":1,"x2":0,"y2":0,"w2":0,"h2":0,"a":7},"row":2,"col":5,"keycodes":[{"id":"KC_N","fields":[]},{"id":"KC_RABK","fields":[]},{"id":"LCTL()","fields":[{"id":"LALT()","fields":[{"id":"KC_DEL","fields":[]}]}]},{"id":"KC_TRNS","fields":[]},{"id":"KC_TRNS","fields":[]},{"id":"KC_TRNS","fields":[]},{"id":"KC_TRNS","fields":[]},{"id":"KC_TRNS","fields":[]},{"id":"KC_TRNS","fields":[]},{"id":"KC_TRNS","fields":[]},{"id":"KC_TRNS","fields":[]},{"id":"KC_TRNS","fields":[]},{"id":"KC_TRNS","fields":[]},{"id":"KC_TRNS","fields":[]},{"id":"KC_TRNS","fields":[]},{"id":"KC_TRNS","fields":[]}]},{"id":28,"legend":"M","state":{"x":6,"y":2,"r":0,"rx":0,"ry":0,"w":1,"h":1,"x2":0,"y2":0,"w2":0,"h2":0,"a":7},"row":2,"col":6,"keycodes":[{"id":"KC_M","fields":[]},{"id":"KC_ENT","fields":[]},{"id":"RGB_VAI","fields":[]},{"id":"KC_TRNS","fields":[]},{"id":"KC_TRNS","fields":[]},{"id":"KC_TRNS","fields":[]},{"id":"KC_TRNS","fields":[]},{"id":"KC_TRNS","fields":[]},{"id":"KC_TRNS","fields":[]},{"id":"KC_TRNS","fields":[]},{"id":"KC_TRNS","fields":[]},{"id":"KC_TRNS","fields":[]},{"id":"KC_TRNS","fields":[]},{"id":"KC_TRNS","fields":[]},{"id":"KC_TRNS","fields":[]},{"id":"KC_TRNS","fields":[]}]},{"id":29,"legend":",","state":{"x":7,"y":2,"r":0,"rx":0,"ry":0,"w":1,"h":1,"x2":0,"y2":0,"w2":0,"h2":0,"a":7},"row":2,"col":7,"keycodes":[{"id":"KC_SPC","fields":[]},{"id":"KC_DOWN","fields":[]},{"id":"RGB_VAD","fields":[]},{"id":"KC_TRNS","fields":[]},{"id":"KC_TRNS","fields":[]},{"id":"KC_TRNS","fields":[]},{"id":"KC_TRNS","fields":[]},{"id":"KC_TRNS","fields":[]},{"id":"KC_TRNS","fields":[]},{"id":"KC_TRNS","fields":[]},{"id":"KC_TRNS","fields":[]},{"id":"KC_TRNS","fields":[]},{"id":"KC_TRNS","fields":[]},{"id":"KC_TRNS","fields":[]},{"id":"KC_TRNS","fields":[]},{"id":"KC_TRNS","fields":[]}]},{"id":30,"legend":".","state":{"x":8,"y":2,"r":0,"rx":0,"ry":0,"w":1,"h":1,"x2":0,"y2":0,"w2":0,"h2":0,"a":7},"row":2,"col":8,"keycodes":[{"id":"KC_DOT","fields":[]},{"id":"KC_COMM","fields":[]},{"id":"RGB_MOD","fields":[]},{"id":"KC_TRNS","fields":[]},{"id":"KC_TRNS","fields":[]},{"id":"KC_TRNS","fields":[]},{"id":"KC_TRNS","fields":[]},{"id":"KC_TRNS","fields":[]},{"id":"KC_TRNS","fields":[]},{"id":"KC_TRNS","fields":[]},{"id":"KC_TRNS","fields":[]},{"id":"KC_TRNS","fields":[]},{"id":"KC_TRNS","fields":[]},{"id":"KC_TRNS","fields":[]},{"id":"KC_TRNS","fields":[]},{"id":"KC_TRNS","fields":[]}]},{"id":31,"legend":"/","state":{"x":9,"y":2,"r":0,"rx":0,"ry":0,"w":1,"h":1,"x2":0,"y2":0,"w2":0,"h2":0,"a":7},"row":2,"col":9,"keycodes":[{"id":"MO()","fields":[1]},{"id":"KC_TRNS","fields":[]},{"id":"RGB_TOG","fields":[]},{"id":"KC_TRNS","fields":[]},{"id":"KC_TRNS","fields":[]},{"id":"KC_TRNS","fields":[]},{"id":"KC_TRNS","fields":[]},{"id":"KC_TRNS","fields":[]},{"id":"KC_TRNS","fields":[]},{"id":"KC_TRNS","fields":[]},{"id":"KC_TRNS","fields":[]},{"id":"KC_TRNS","fields":[]},{"id":"KC_TRNS","fields":[]},{"id":"KC_TRNS","fields":[]},{"id":"KC_TRNS","fields":[]},{"id":"KC_TRNS","fields":[]}]},{"id":32,"legend":"Return","state":{"x":10,"y":2,"r":0,"rx":0,"ry":0,"w":1,"h":1,"x2":0,"y2":0,"w2":0,"h2":0,"a":7},"row":2,"col":10,"keycodes":[{"id":"MO()","fields":[2]},{"id":"KC_MUTE","fields":[]},{"id":"KC_TRNS","fields":[]},{"id":"KC_TRNS","fields":[]},{"id":"KC_TRNS","fields":[]},{"id":"KC_TRNS","fields":[]},{"id":"KC_TRNS","fields":[]},{"id":"KC_TRNS","fields":[]},{"id":"KC_TRNS","fields":[]},{"id":"KC_TRNS","fields":[]},{"id":"KC_TRNS","fields":[]},{"id":"KC_TRNS","fields":[]},{"id":"KC_TRNS","fields":[]},{"id":"KC_TRNS","fields":[]},{"id":"KC_TRNS","fields":[]},{"id":"KC_TRNS","fields":[]}]}],"controller":1,"bounds":{"min":{"x":0,"y":0},"max":{"x":11,"y":3}},"rows":3,"cols":11,"pins":{"row":["F0","F4","D7"],"col":["C6","C7","F7","F6","F1","E6","B7","B3","B2","B1","B0"],"num":null,"caps":null,"scroll":null,"compose":null,"kana":null,"led":null,"rgb":"D0"},"macros":{},"quantum":"void matrix_init_user(void) {\n}\n\nvoid matrix_scan_user(void) {\n}\n\nbool process_record_user(uint16_t keycode, keyrecord_t *record) {\n\treturn true;\n}","settings":{"diodeDirection":1,"name":"miuni32","bootloaderSize":2,"rgbNum":7,"backlightLevels":0}}}
